{
  "cli": {
    "version": ">= 10.0.0"
  },
  "build": {
    "development": {
      "developmentClient": true,
      "distribution": "internal"
    },
    "preview": {
      "distribution": "internal",
      "ios": {
        "simulator": true
      },
      "android": {
        "buildType": "apk"
      }
    },
    "production": {
      "ios": {
        "autoIncrement": true,
        "appleId": "rebuild.up.up@gmail.com",
        "ascAppId": "",
        "teamId": "JK49RJ2CK2",
        "enterpriseProvProfileUUID": "",
        "provisioningProfileSpecifier": ""
      },
      "android": {
        "autoIncrement": true
      }
    }
  }
}
